minify_html_fallback-0.16.4.dist-info/METADATA
minify_html_fallback-0.16.4.dist-info/WHEEL
minify_html_fallback/__init__.py
minify_html_fallback/minify_html_fallback.cpython-310-aarch64-linux-gnu.so
minify_html_fallback-0.16.4.dist-info/RECORD
