Metadata-Version: 2.4
Name: minify_html_fallback
Version: 0.16.4
Summary: Extremely fast and smart HTML + JS + CSS minifier
Home-Page: https://github.com/wilsonzlin/minify-html
Author: Wilson Lin <code@wilsonl.in>
Author-email: Wilson Lin <code@wilsonl.in>
License: MIT
Project-URL: Source Code, https://github.com/wilsonzlin/minify-html.git
